{"efVersion":"0.13.5","efModuleName":["Effect","Unsafe"],"efExports":[{"ValueRef":[{"start":[1,1],"name":".spago/effect/v2.0.1/src/Effect/Unsafe.purs","end":[8,62]},{"Ident":"unsafePerformEffect"}]}],"efImports":[{"eiModule":["Prim"],"eiImportType":{"Implicit":[]},"eiImportedAs":["Prim"]},{"eiModule":["Prim"],"eiImportType":{"Implicit":[]},"eiImportedAs":null},{"eiModule":["Effect"],"eiImportType":{"Explicit":[{"TypeRef":[{"start":[3,16],"name":".spago/effect/v2.0.1/src/Effect/Unsafe.purs","end":[3,22]},"Effect",[]]}]},"eiImportedAs":null}],"efFixities":[],"efTypeFixities":[],"efDeclarations":[{"EDValue":{"edValueName":{"Ident":"unsafePerformEffect"},"edValueType":{"annotation":[{"start":[8,39],"name":".spago/effect/v2.0.1/src/Effect/Unsafe.purs","end":[8,62]},[]],"tag":"ForAll","contents":["a",{"annotation":[{"start":[8,49],"name":".spago/effect/v2.0.1/src/Effect/Unsafe.purs","end":[8,62]},[]],"tag":"TypeApp","contents":[{"annotation":[{"start":[8,49],"name":".spago/effect/v2.0.1/src/Effect/Unsafe.purs","end":[8,62]},[]],"tag":"TypeApp","contents":[{"annotation":[{"start":[8,58],"name":".spago/effect/v2.0.1/src/Effect/Unsafe.purs","end":[8,60]},[]],"tag":"TypeConstructor","contents":[["Prim"],"Function"]},{"annotation":[{"start":[8,49],"name":".spago/effect/v2.0.1/src/Effect/Unsafe.purs","end":[8,57]},[]],"tag":"TypeApp","contents":[{"annotation":[{"start":[8,49],"name":".spago/effect/v2.0.1/src/Effect/Unsafe.purs","end":[8,55]},[]],"tag":"TypeConstructor","contents":[["Effect"],"Effect"]},{"annotation":[{"start":[8,56],"name":".spago/effect/v2.0.1/src/Effect/Unsafe.purs","end":[8,57]},[]],"tag":"TypeVar","contents":"a"}]}]},{"annotation":[{"start":[8,61],"name":".spago/effect/v2.0.1/src/Effect/Unsafe.purs","end":[8,62]},[]],"tag":"TypeVar","contents":"a"}]},null]}}}],"efSourceSpan":{"start":[1,1],"name":".spago/effect/v2.0.1/src/Effect/Unsafe.purs","end":[8,62]}}