{"efVersion":"0.13.5","efModuleName":["Egg","Types","Clockwise"],"efExports":[{"TypeRef":[{"start":[1,1],"name":"src/types/Clockwise.purs","end":[16,39]},"Clockwise",["Clockwise","AntiClockwise"]]},{"TypeInstanceRef":[{"start":[0,0],"name":"<generated>","end":[0,0]},{"Ident":"eqClockwise"}]},{"TypeInstanceRef":[{"start":[0,0],"name":"<generated>","end":[0,0]},{"Ident":"ordClockwise"}]},{"TypeInstanceRef":[{"start":[0,0],"name":"<generated>","end":[0,0]},{"Ident":"showClockwise"}]}],"efImports":[{"eiModule":["Prim"],"eiImportType":{"Implicit":[]},"eiImportedAs":["Prim"]},{"eiModule":["Prim"],"eiImportType":{"Implicit":[]},"eiImportedAs":null},{"eiModule":["Data","Eq"],"eiImportType":{"Implicit":[]},"eiImportedAs":null},{"eiModule":["Data","Ord"],"eiImportType":{"Implicit":[]},"eiImportedAs":null},{"eiModule":["Data","Show"],"eiImportType":{"Implicit":[]},"eiImportedAs":null}],"efFixities":[],"efTypeFixities":[],"efDeclarations":[{"EDType":{"edTypeName":"Clockwise","edTypeKind":{"annotation":[{"start":[0,0],"name":"","end":[0,0]},[]],"tag":"NamedKind","contents":[["Prim"],"Type"]},"edTypeDeclarationKind":{"DataType":{"args":[],"ctors":[["Clockwise",[]],["AntiClockwise",[]]]}}}},{"EDDataConstructor":{"edDataCtorName":"Clockwise","edDataCtorOrigin":"data","edDataCtorTypeCtor":"Clockwise","edDataCtorType":{"annotation":[{"start":[0,0],"name":"","end":[0,0]},[]],"tag":"TypeConstructor","contents":[["Egg","Types","Clockwise"],"Clockwise"]},"edDataCtorFields":[]}},{"EDDataConstructor":{"edDataCtorName":"AntiClockwise","edDataCtorOrigin":"data","edDataCtorTypeCtor":"Clockwise","edDataCtorType":{"annotation":[{"start":[0,0],"name":"","end":[0,0]},[]],"tag":"TypeConstructor","contents":[["Egg","Types","Clockwise"],"Clockwise"]},"edDataCtorFields":[]}},{"EDInstance":{"edInstanceClassName":[["Data","Eq"],"Eq"],"edInstanceName":{"Ident":"eqClockwise"},"edInstanceTypes":[{"annotation":[{"start":[11,35],"name":"src/types/Clockwise.purs","end":[11,44]},[]],"tag":"TypeConstructor","contents":[["Egg","Types","Clockwise"],"Clockwise"]}],"edInstanceConstraints":[],"edInstanceChain":[[["Egg","Types","Clockwise"],{"Ident":"eqClockwise"}]],"edInstanceChainIndex":0}},{"EDInstance":{"edInstanceClassName":[["Data","Ord"],"Ord"],"edInstanceName":{"Ident":"ordClockwise"},"edInstanceTypes":[{"annotation":[{"start":[12,37],"name":"src/types/Clockwise.purs","end":[12,46]},[]],"tag":"TypeConstructor","contents":[["Egg","Types","Clockwise"],"Clockwise"]}],"edInstanceConstraints":[],"edInstanceChain":[[["Egg","Types","Clockwise"],{"Ident":"ordClockwise"}]],"edInstanceChainIndex":0}},{"EDInstance":{"edInstanceClassName":[["Data","Show"],"Show"],"edInstanceName":{"Ident":"showClockwise"},"edInstanceTypes":[{"annotation":[{"start":[14,32],"name":"src/types/Clockwise.purs","end":[14,41]},[]],"tag":"TypeConstructor","contents":[["Egg","Types","Clockwise"],"Clockwise"]}],"edInstanceConstraints":[],"edInstanceChain":[[["Egg","Types","Clockwise"],{"Ident":"showClockwise"}]],"edInstanceChainIndex":0}}],"efSourceSpan":{"start":[1,1],"name":"src/types/Clockwise.purs","end":[16,39]}}