{"efVersion":"0.13.5","efModuleName":["Data","String","Gen"],"efExports":[{"ValueRef":[{"start":[1,1],"name":".spago/strings/v4.0.1/src/Data/String/Gen.purs","end":[43,57]},{"Ident":"genString"}]},{"ValueRef":[{"start":[1,1],"name":".spago/strings/v4.0.1/src/Data/String/Gen.purs","end":[43,57]},{"Ident":"genUnicodeString"}]},{"ValueRef":[{"start":[1,1],"name":".spago/strings/v4.0.1/src/Data/String/Gen.purs","end":[43,57]},{"Ident":"genAsciiString"}]},{"ValueRef":[{"start":[1,1],"name":".spago/strings/v4.0.1/src/Data/String/Gen.purs","end":[43,57]},{"Ident":"genAsciiString'"}]},{"ValueRef":[{"start":[1,1],"name":".spago/strings/v4.0.1/src/Data/String/Gen.purs","end":[43,57]},{"Ident":"genDigitString"}]},{"ValueRef":[{"start":[1,1],"name":".spago/strings/v4.0.1/src/Data/String/Gen.purs","end":[43,57]},{"Ident":"genAlphaString"}]},{"ValueRef":[{"start":[1,1],"name":".spago/strings/v4.0.1/src/Data/String/Gen.purs","end":[43,57]},{"Ident":"genAlphaLowercaseString"}]},{"ValueRef":[{"start":[1,1],"name":".spago/strings/v4.0.1/src/Data/String/Gen.purs","end":[43,57]},{"Ident":"genAlphaUppercaseString"}]}],"efImports":[{"eiModule":["Prim"],"eiImportType":{"Implicit":[]},"eiImportedAs":["Prim"]},{"eiModule":["Prim"],"eiImportType":{"Implicit":[]},"eiImportedAs":null},{"eiModule":["Prelude"],"eiImportType":{"Implicit":[]},"eiImportedAs":null},{"eiModule":["Control","Monad","Gen"],"eiImportType":{"Explicit":[{"TypeClassRef":[{"start":[5,27],"name":".spago/strings/v4.0.1/src/Data/String/Gen.purs","end":[5,41]},"MonadGen"]},{"ValueRef":[{"start":[5,43],"name":".spago/strings/v4.0.1/src/Data/String/Gen.purs","end":[5,52]},{"Ident":"chooseInt"}]},{"ValueRef":[{"start":[5,54],"name":".spago/strings/v4.0.1/src/Data/String/Gen.purs","end":[5,64]},{"Ident":"unfoldable"}]},{"ValueRef":[{"start":[5,66],"name":".spago/strings/v4.0.1/src/Data/String/Gen.purs","end":[5,71]},{"Ident":"sized"}]},{"ValueRef":[{"start":[5,73],"name":".spago/strings/v4.0.1/src/Data/String/Gen.purs","end":[5,79]},{"Ident":"resize"}]}]},"eiImportedAs":null},{"eiModule":["Control","Monad","Rec","Class"],"eiImportType":{"Explicit":[{"TypeClassRef":[{"start":[6,33],"name":".spago/strings/v4.0.1/src/Data/String/Gen.purs","end":[6,47]},"MonadRec"]}]},"eiImportedAs":null},{"eiModule":["Data","Char","Gen"],"eiImportType":{"Implicit":[]},"eiImportedAs":["CG"]},{"eiModule":["Data","String","CodeUnits"],"eiImportType":{"Implicit":[]},"eiImportedAs":["SCU"]}],"efFixities":[],"efTypeFixities":[],"efDeclarations":[{"EDValue":{"edValueName":{"Ident":"genString"},"edValueType":{"annotation":[{"start":[11,14],"name":".spago/strings/v4.0.1/src/Data/String/Gen.purs","end":[11,70]},[]],"tag":"ForAll","contents":["m",{"annotation":[{"start":[11,24],"name":".spago/strings/v4.0.1/src/Data/String/Gen.purs","end":[11,70]},[]],"tag":"ConstrainedType","contents":[{"constraintAnn":[{"start":[11,24],"name":".spago/strings/v4.0.1/src/Data/String/Gen.purs","end":[11,34]},[]],"constraintClass":[["Control","Monad","Rec","Class"],"MonadRec"],"constraintArgs":[{"annotation":[{"start":[11,33],"name":".spago/strings/v4.0.1/src/Data/String/Gen.purs","end":[11,34]},[]],"tag":"TypeVar","contents":"m"}],"constraintData":null},{"annotation":[{"start":[11,38],"name":".spago/strings/v4.0.1/src/Data/String/Gen.purs","end":[11,70]},[]],"tag":"ConstrainedType","contents":[{"constraintAnn":[{"start":[11,38],"name":".spago/strings/v4.0.1/src/Data/String/Gen.purs","end":[11,48]},[]],"constraintClass":[["Control","Monad","Gen","Class"],"MonadGen"],"constraintArgs":[{"annotation":[{"start":[11,47],"name":".spago/strings/v4.0.1/src/Data/String/Gen.purs","end":[11,48]},[]],"tag":"TypeVar","contents":"m"}],"constraintData":null},{"annotation":[{"start":[11,52],"name":".spago/strings/v4.0.1/src/Data/String/Gen.purs","end":[11,70]},[]],"tag":"TypeApp","contents":[{"annotation":[{"start":[11,52],"name":".spago/strings/v4.0.1/src/Data/String/Gen.purs","end":[11,70]},[]],"tag":"TypeApp","contents":[{"annotation":[{"start":[11,59],"name":".spago/strings/v4.0.1/src/Data/String/Gen.purs","end":[11,61]},[]],"tag":"TypeConstructor","contents":[["Prim"],"Function"]},{"annotation":[{"start":[11,52],"name":".spago/strings/v4.0.1/src/Data/String/Gen.purs","end":[11,58]},[]],"tag":"TypeApp","contents":[{"annotation":[{"start":[11,52],"name":".spago/strings/v4.0.1/src/Data/String/Gen.purs","end":[11,53]},[]],"tag":"TypeVar","contents":"m"},{"annotation":[{"start":[11,54],"name":".spago/strings/v4.0.1/src/Data/String/Gen.purs","end":[11,58]},[]],"tag":"TypeConstructor","contents":[["Prim"],"Char"]}]}]},{"annotation":[{"start":[11,62],"name":".spago/strings/v4.0.1/src/Data/String/Gen.purs","end":[11,70]},[]],"tag":"TypeApp","contents":[{"annotation":[{"start":[11,62],"name":".spago/strings/v4.0.1/src/Data/String/Gen.purs","end":[11,63]},[]],"tag":"TypeVar","contents":"m"},{"annotation":[{"start":[11,64],"name":".spago/strings/v4.0.1/src/Data/String/Gen.purs","end":[11,70]},[]],"tag":"TypeConstructor","contents":[["Prim"],"String"]}]}]}]}]},0]}}},{"EDValue":{"edValueName":{"Ident":"genUnicodeString"},"edValueType":{"annotation":[{"start":[18,21],"name":".spago/strings/v4.0.1/src/Data/String/Gen.purs","end":[18,67]},[]],"tag":"ForAll","contents":["m",{"annotation":[{"start":[18,31],"name":".spago/strings/v4.0.1/src/Data/String/Gen.purs","end":[18,67]},[]],"tag":"ConstrainedType","contents":[{"constraintAnn":[{"start":[18,31],"name":".spago/strings/v4.0.1/src/Data/String/Gen.purs","end":[18,41]},[]],"constraintClass":[["Control","Monad","Rec","Class"],"MonadRec"],"constraintArgs":[{"annotation":[{"start":[18,40],"name":".spago/strings/v4.0.1/src/Data/String/Gen.purs","end":[18,41]},[]],"tag":"TypeVar","contents":"m"}],"constraintData":null},{"annotation":[{"start":[18,45],"name":".spago/strings/v4.0.1/src/Data/String/Gen.purs","end":[18,67]},[]],"tag":"ConstrainedType","contents":[{"constraintAnn":[{"start":[18,45],"name":".spago/strings/v4.0.1/src/Data/String/Gen.purs","end":[18,55]},[]],"constraintClass":[["Control","Monad","Gen","Class"],"MonadGen"],"constraintArgs":[{"annotation":[{"start":[18,54],"name":".spago/strings/v4.0.1/src/Data/String/Gen.purs","end":[18,55]},[]],"tag":"TypeVar","contents":"m"}],"constraintData":null},{"annotation":[{"start":[18,59],"name":".spago/strings/v4.0.1/src/Data/String/Gen.purs","end":[18,67]},[]],"tag":"TypeApp","contents":[{"annotation":[{"start":[18,59],"name":".spago/strings/v4.0.1/src/Data/String/Gen.purs","end":[18,60]},[]],"tag":"TypeVar","contents":"m"},{"annotation":[{"start":[18,61],"name":".spago/strings/v4.0.1/src/Data/String/Gen.purs","end":[18,67]},[]],"tag":"TypeConstructor","contents":[["Prim"],"String"]}]}]}]},2]}}},{"EDValue":{"edValueName":{"Ident":"genAsciiString"},"edValueType":{"annotation":[{"start":[22,19],"name":".spago/strings/v4.0.1/src/Data/String/Gen.purs","end":[22,65]},[]],"tag":"ForAll","contents":["m",{"annotation":[{"start":[22,29],"name":".spago/strings/v4.0.1/src/Data/String/Gen.purs","end":[22,65]},[]],"tag":"ConstrainedType","contents":[{"constraintAnn":[{"start":[22,29],"name":".spago/strings/v4.0.1/src/Data/String/Gen.purs","end":[22,39]},[]],"constraintClass":[["Control","Monad","Rec","Class"],"MonadRec"],"constraintArgs":[{"annotation":[{"start":[22,38],"name":".spago/strings/v4.0.1/src/Data/String/Gen.purs","end":[22,39]},[]],"tag":"TypeVar","contents":"m"}],"constraintData":null},{"annotation":[{"start":[22,43],"name":".spago/strings/v4.0.1/src/Data/String/Gen.purs","end":[22,65]},[]],"tag":"ConstrainedType","contents":[{"constraintAnn":[{"start":[22,43],"name":".spago/strings/v4.0.1/src/Data/String/Gen.purs","end":[22,53]},[]],"constraintClass":[["Control","Monad","Gen","Class"],"MonadGen"],"constraintArgs":[{"annotation":[{"start":[22,52],"name":".spago/strings/v4.0.1/src/Data/String/Gen.purs","end":[22,53]},[]],"tag":"TypeVar","contents":"m"}],"constraintData":null},{"annotation":[{"start":[22,57],"name":".spago/strings/v4.0.1/src/Data/String/Gen.purs","end":[22,65]},[]],"tag":"TypeApp","contents":[{"annotation":[{"start":[22,57],"name":".spago/strings/v4.0.1/src/Data/String/Gen.purs","end":[22,58]},[]],"tag":"TypeVar","contents":"m"},{"annotation":[{"start":[22,59],"name":".spago/strings/v4.0.1/src/Data/String/Gen.purs","end":[22,65]},[]],"tag":"TypeConstructor","contents":[["Prim"],"String"]}]}]}]},8]}}},{"EDValue":{"edValueName":{"Ident":"genAsciiString'"},"edValueType":{"annotation":[{"start":[26,20],"name":".spago/strings/v4.0.1/src/Data/String/Gen.purs","end":[26,66]},[]],"tag":"ForAll","contents":["m",{"annotation":[{"start":[26,30],"name":".spago/strings/v4.0.1/src/Data/String/Gen.purs","end":[26,66]},[]],"tag":"ConstrainedType","contents":[{"constraintAnn":[{"start":[26,30],"name":".spago/strings/v4.0.1/src/Data/String/Gen.purs","end":[26,40]},[]],"constraintClass":[["Control","Monad","Rec","Class"],"MonadRec"],"constraintArgs":[{"annotation":[{"start":[26,39],"name":".spago/strings/v4.0.1/src/Data/String/Gen.purs","end":[26,40]},[]],"tag":"TypeVar","contents":"m"}],"constraintData":null},{"annotation":[{"start":[26,44],"name":".spago/strings/v4.0.1/src/Data/String/Gen.purs","end":[26,66]},[]],"tag":"ConstrainedType","contents":[{"constraintAnn":[{"start":[26,44],"name":".spago/strings/v4.0.1/src/Data/String/Gen.purs","end":[26,54]},[]],"constraintClass":[["Control","Monad","Gen","Class"],"MonadGen"],"constraintArgs":[{"annotation":[{"start":[26,53],"name":".spago/strings/v4.0.1/src/Data/String/Gen.purs","end":[26,54]},[]],"tag":"TypeVar","contents":"m"}],"constraintData":null},{"annotation":[{"start":[26,58],"name":".spago/strings/v4.0.1/src/Data/String/Gen.purs","end":[26,66]},[]],"tag":"TypeApp","contents":[{"annotation":[{"start":[26,58],"name":".spago/strings/v4.0.1/src/Data/String/Gen.purs","end":[26,59]},[]],"tag":"TypeVar","contents":"m"},{"annotation":[{"start":[26,60],"name":".spago/strings/v4.0.1/src/Data/String/Gen.purs","end":[26,66]},[]],"tag":"TypeConstructor","contents":[["Prim"],"String"]}]}]}]},6]}}},{"EDValue":{"edValueName":{"Ident":"genDigitString"},"edValueType":{"annotation":[{"start":[30,19],"name":".spago/strings/v4.0.1/src/Data/String/Gen.purs","end":[30,65]},[]],"tag":"ForAll","contents":["m",{"annotation":[{"start":[30,29],"name":".spago/strings/v4.0.1/src/Data/String/Gen.purs","end":[30,65]},[]],"tag":"ConstrainedType","contents":[{"constraintAnn":[{"start":[30,29],"name":".spago/strings/v4.0.1/src/Data/String/Gen.purs","end":[30,39]},[]],"constraintClass":[["Control","Monad","Rec","Class"],"MonadRec"],"constraintArgs":[{"annotation":[{"start":[30,38],"name":".spago/strings/v4.0.1/src/Data/String/Gen.purs","end":[30,39]},[]],"tag":"TypeVar","contents":"m"}],"constraintData":null},{"annotation":[{"start":[30,43],"name":".spago/strings/v4.0.1/src/Data/String/Gen.purs","end":[30,65]},[]],"tag":"ConstrainedType","contents":[{"constraintAnn":[{"start":[30,43],"name":".spago/strings/v4.0.1/src/Data/String/Gen.purs","end":[30,53]},[]],"constraintClass":[["Control","Monad","Gen","Class"],"MonadGen"],"constraintArgs":[{"annotation":[{"start":[30,52],"name":".spago/strings/v4.0.1/src/Data/String/Gen.purs","end":[30,53]},[]],"tag":"TypeVar","contents":"m"}],"constraintData":null},{"annotation":[{"start":[30,57],"name":".spago/strings/v4.0.1/src/Data/String/Gen.purs","end":[30,65]},[]],"tag":"TypeApp","contents":[{"annotation":[{"start":[30,57],"name":".spago/strings/v4.0.1/src/Data/String/Gen.purs","end":[30,58]},[]],"tag":"TypeVar","contents":"m"},{"annotation":[{"start":[30,59],"name":".spago/strings/v4.0.1/src/Data/String/Gen.purs","end":[30,65]},[]],"tag":"TypeConstructor","contents":[["Prim"],"String"]}]}]}]},4]}}},{"EDValue":{"edValueName":{"Ident":"genAlphaString"},"edValueType":{"annotation":[{"start":[34,19],"name":".spago/strings/v4.0.1/src/Data/String/Gen.purs","end":[34,65]},[]],"tag":"ForAll","contents":["m",{"annotation":[{"start":[34,29],"name":".spago/strings/v4.0.1/src/Data/String/Gen.purs","end":[34,65]},[]],"tag":"ConstrainedType","contents":[{"constraintAnn":[{"start":[34,29],"name":".spago/strings/v4.0.1/src/Data/String/Gen.purs","end":[34,39]},[]],"constraintClass":[["Control","Monad","Rec","Class"],"MonadRec"],"constraintArgs":[{"annotation":[{"start":[34,38],"name":".spago/strings/v4.0.1/src/Data/String/Gen.purs","end":[34,39]},[]],"tag":"TypeVar","contents":"m"}],"constraintData":null},{"annotation":[{"start":[34,43],"name":".spago/strings/v4.0.1/src/Data/String/Gen.purs","end":[34,65]},[]],"tag":"ConstrainedType","contents":[{"constraintAnn":[{"start":[34,43],"name":".spago/strings/v4.0.1/src/Data/String/Gen.purs","end":[34,53]},[]],"constraintClass":[["Control","Monad","Gen","Class"],"MonadGen"],"constraintArgs":[{"annotation":[{"start":[34,52],"name":".spago/strings/v4.0.1/src/Data/String/Gen.purs","end":[34,53]},[]],"tag":"TypeVar","contents":"m"}],"constraintData":null},{"annotation":[{"start":[34,57],"name":".spago/strings/v4.0.1/src/Data/String/Gen.purs","end":[34,65]},[]],"tag":"TypeApp","contents":[{"annotation":[{"start":[34,57],"name":".spago/strings/v4.0.1/src/Data/String/Gen.purs","end":[34,58]},[]],"tag":"TypeVar","contents":"m"},{"annotation":[{"start":[34,59],"name":".spago/strings/v4.0.1/src/Data/String/Gen.purs","end":[34,65]},[]],"tag":"TypeConstructor","contents":[["Prim"],"String"]}]}]}]},12]}}},{"EDValue":{"edValueName":{"Ident":"genAlphaLowercaseString"},"edValueType":{"annotation":[{"start":[38,28],"name":".spago/strings/v4.0.1/src/Data/String/Gen.purs","end":[38,74]},[]],"tag":"ForAll","contents":["m",{"annotation":[{"start":[38,38],"name":".spago/strings/v4.0.1/src/Data/String/Gen.purs","end":[38,74]},[]],"tag":"ConstrainedType","contents":[{"constraintAnn":[{"start":[38,38],"name":".spago/strings/v4.0.1/src/Data/String/Gen.purs","end":[38,48]},[]],"constraintClass":[["Control","Monad","Rec","Class"],"MonadRec"],"constraintArgs":[{"annotation":[{"start":[38,47],"name":".spago/strings/v4.0.1/src/Data/String/Gen.purs","end":[38,48]},[]],"tag":"TypeVar","contents":"m"}],"constraintData":null},{"annotation":[{"start":[38,52],"name":".spago/strings/v4.0.1/src/Data/String/Gen.purs","end":[38,74]},[]],"tag":"ConstrainedType","contents":[{"constraintAnn":[{"start":[38,52],"name":".spago/strings/v4.0.1/src/Data/String/Gen.purs","end":[38,62]},[]],"constraintClass":[["Control","Monad","Gen","Class"],"MonadGen"],"constraintArgs":[{"annotation":[{"start":[38,61],"name":".spago/strings/v4.0.1/src/Data/String/Gen.purs","end":[38,62]},[]],"tag":"TypeVar","contents":"m"}],"constraintData":null},{"annotation":[{"start":[38,66],"name":".spago/strings/v4.0.1/src/Data/String/Gen.purs","end":[38,74]},[]],"tag":"TypeApp","contents":[{"annotation":[{"start":[38,66],"name":".spago/strings/v4.0.1/src/Data/String/Gen.purs","end":[38,67]},[]],"tag":"TypeVar","contents":"m"},{"annotation":[{"start":[38,68],"name":".spago/strings/v4.0.1/src/Data/String/Gen.purs","end":[38,74]},[]],"tag":"TypeConstructor","contents":[["Prim"],"String"]}]}]}]},14]}}},{"EDValue":{"edValueName":{"Ident":"genAlphaUppercaseString"},"edValueType":{"annotation":[{"start":[42,28],"name":".spago/strings/v4.0.1/src/Data/String/Gen.purs","end":[42,74]},[]],"tag":"ForAll","contents":["m",{"annotation":[{"start":[42,38],"name":".spago/strings/v4.0.1/src/Data/String/Gen.purs","end":[42,74]},[]],"tag":"ConstrainedType","contents":[{"constraintAnn":[{"start":[42,38],"name":".spago/strings/v4.0.1/src/Data/String/Gen.purs","end":[42,48]},[]],"constraintClass":[["Control","Monad","Rec","Class"],"MonadRec"],"constraintArgs":[{"annotation":[{"start":[42,47],"name":".spago/strings/v4.0.1/src/Data/String/Gen.purs","end":[42,48]},[]],"tag":"TypeVar","contents":"m"}],"constraintData":null},{"annotation":[{"start":[42,52],"name":".spago/strings/v4.0.1/src/Data/String/Gen.purs","end":[42,74]},[]],"tag":"ConstrainedType","contents":[{"constraintAnn":[{"start":[42,52],"name":".spago/strings/v4.0.1/src/Data/String/Gen.purs","end":[42,62]},[]],"constraintClass":[["Control","Monad","Gen","Class"],"MonadGen"],"constraintArgs":[{"annotation":[{"start":[42,61],"name":".spago/strings/v4.0.1/src/Data/String/Gen.purs","end":[42,62]},[]],"tag":"TypeVar","contents":"m"}],"constraintData":null},{"annotation":[{"start":[42,66],"name":".spago/strings/v4.0.1/src/Data/String/Gen.purs","end":[42,74]},[]],"tag":"TypeApp","contents":[{"annotation":[{"start":[42,66],"name":".spago/strings/v4.0.1/src/Data/String/Gen.purs","end":[42,67]},[]],"tag":"TypeVar","contents":"m"},{"annotation":[{"start":[42,68],"name":".spago/strings/v4.0.1/src/Data/String/Gen.purs","end":[42,74]},[]],"tag":"TypeConstructor","contents":[["Prim"],"String"]}]}]}]},10]}}}],"efSourceSpan":{"start":[1,1],"name":".spago/strings/v4.0.1/src/Data/String/Gen.purs","end":[43,57]}}