{"efVersion":"0.13.5","efModuleName":["Web","UIEvent","InputEvent"],"efExports":[{"TypeRef":[{"start":[1,1],"name":".spago/web-uievents/v2.0.0/src/Web/UIEvent/InputEvent.purs","end":[25,52]},"InputEvent",[]]},{"ValueRef":[{"start":[1,1],"name":".spago/web-uievents/v2.0.0/src/Web/UIEvent/InputEvent.purs","end":[25,52]},{"Ident":"fromUIEvent"}]},{"ValueRef":[{"start":[1,1],"name":".spago/web-uievents/v2.0.0/src/Web/UIEvent/InputEvent.purs","end":[25,52]},{"Ident":"fromEvent"}]},{"ValueRef":[{"start":[1,1],"name":".spago/web-uievents/v2.0.0/src/Web/UIEvent/InputEvent.purs","end":[25,52]},{"Ident":"toUIEvent"}]},{"ValueRef":[{"start":[1,1],"name":".spago/web-uievents/v2.0.0/src/Web/UIEvent/InputEvent.purs","end":[25,52]},{"Ident":"toEvent"}]},{"ValueRef":[{"start":[1,1],"name":".spago/web-uievents/v2.0.0/src/Web/UIEvent/InputEvent.purs","end":[25,52]},{"Ident":"data_"}]},{"ValueRef":[{"start":[1,1],"name":".spago/web-uievents/v2.0.0/src/Web/UIEvent/InputEvent.purs","end":[25,52]},{"Ident":"isComposing"}]}],"efImports":[{"eiModule":["Prim"],"eiImportType":{"Implicit":[]},"eiImportedAs":["Prim"]},{"eiModule":["Prim"],"eiImportType":{"Implicit":[]},"eiImportedAs":null},{"eiModule":["Data","Maybe"],"eiImportType":{"Explicit":[{"TypeRef":[{"start":[3,20],"name":".spago/web-uievents/v2.0.0/src/Web/UIEvent/InputEvent.purs","end":[3,25]},"Maybe",[]]}]},"eiImportedAs":null},{"eiModule":["Unsafe","Coerce"],"eiImportType":{"Explicit":[{"ValueRef":[{"start":[4,23],"name":".spago/web-uievents/v2.0.0/src/Web/UIEvent/InputEvent.purs","end":[4,35]},{"Ident":"unsafeCoerce"}]}]},"eiImportedAs":null},{"eiModule":["Web","Event","Event"],"eiImportType":{"Explicit":[{"TypeRef":[{"start":[5,25],"name":".spago/web-uievents/v2.0.0/src/Web/UIEvent/InputEvent.purs","end":[5,30]},"Event",[]]}]},"eiImportedAs":null},{"eiModule":["Web","Internal","FFI"],"eiImportType":{"Explicit":[{"ValueRef":[{"start":[6,26],"name":".spago/web-uievents/v2.0.0/src/Web/UIEvent/InputEvent.purs","end":[6,47]},{"Ident":"unsafeReadProtoTagged"}]}]},"eiImportedAs":null},{"eiModule":["Web","UIEvent","UIEvent"],"eiImportType":{"Explicit":[{"TypeRef":[{"start":[7,29],"name":".spago/web-uievents/v2.0.0/src/Web/UIEvent/InputEvent.purs","end":[7,36]},"UIEvent",[]]}]},"eiImportedAs":null}],"efFixities":[],"efTypeFixities":[],"efDeclarations":[{"EDType":{"edTypeName":"InputEvent","edTypeKind":{"annotation":[{"start":[9,35],"name":".spago/web-uievents/v2.0.0/src/Web/UIEvent/InputEvent.purs","end":[9,39]},[]],"tag":"NamedKind","contents":[["Prim"],"Type"]},"edTypeDeclarationKind":"ExternData"}},{"EDValue":{"edValueName":{"Ident":"fromUIEvent"},"edValueType":{"annotation":[{"start":[11,16],"name":".spago/web-uievents/v2.0.0/src/Web/UIEvent/InputEvent.purs","end":[11,43]},[]],"tag":"TypeApp","contents":[{"annotation":[{"start":[11,16],"name":".spago/web-uievents/v2.0.0/src/Web/UIEvent/InputEvent.purs","end":[11,43]},[]],"tag":"TypeApp","contents":[{"annotation":[{"start":[11,24],"name":".spago/web-uievents/v2.0.0/src/Web/UIEvent/InputEvent.purs","end":[11,26]},[]],"tag":"TypeConstructor","contents":[["Prim"],"Function"]},{"annotation":[{"start":[11,16],"name":".spago/web-uievents/v2.0.0/src/Web/UIEvent/InputEvent.purs","end":[11,23]},[]],"tag":"TypeConstructor","contents":[["Web","UIEvent","UIEvent"],"UIEvent"]}]},{"annotation":[{"start":[11,27],"name":".spago/web-uievents/v2.0.0/src/Web/UIEvent/InputEvent.purs","end":[11,43]},[]],"tag":"TypeApp","contents":[{"annotation":[{"start":[11,27],"name":".spago/web-uievents/v2.0.0/src/Web/UIEvent/InputEvent.purs","end":[11,32]},[]],"tag":"TypeConstructor","contents":[["Data","Maybe"],"Maybe"]},{"annotation":[{"start":[11,33],"name":".spago/web-uievents/v2.0.0/src/Web/UIEvent/InputEvent.purs","end":[11,43]},[]],"tag":"TypeConstructor","contents":[["Web","UIEvent","InputEvent"],"InputEvent"]}]}]}}},{"EDValue":{"edValueName":{"Ident":"fromEvent"},"edValueType":{"annotation":[{"start":[14,14],"name":".spago/web-uievents/v2.0.0/src/Web/UIEvent/InputEvent.purs","end":[14,39]},[]],"tag":"TypeApp","contents":[{"annotation":[{"start":[14,14],"name":".spago/web-uievents/v2.0.0/src/Web/UIEvent/InputEvent.purs","end":[14,39]},[]],"tag":"TypeApp","contents":[{"annotation":[{"start":[14,20],"name":".spago/web-uievents/v2.0.0/src/Web/UIEvent/InputEvent.purs","end":[14,22]},[]],"tag":"TypeConstructor","contents":[["Prim"],"Function"]},{"annotation":[{"start":[14,14],"name":".spago/web-uievents/v2.0.0/src/Web/UIEvent/InputEvent.purs","end":[14,19]},[]],"tag":"TypeConstructor","contents":[["Web","Event","Internal","Types"],"Event"]}]},{"annotation":[{"start":[14,23],"name":".spago/web-uievents/v2.0.0/src/Web/UIEvent/InputEvent.purs","end":[14,39]},[]],"tag":"TypeApp","contents":[{"annotation":[{"start":[14,23],"name":".spago/web-uievents/v2.0.0/src/Web/UIEvent/InputEvent.purs","end":[14,28]},[]],"tag":"TypeConstructor","contents":[["Data","Maybe"],"Maybe"]},{"annotation":[{"start":[14,29],"name":".spago/web-uievents/v2.0.0/src/Web/UIEvent/InputEvent.purs","end":[14,39]},[]],"tag":"TypeConstructor","contents":[["Web","UIEvent","InputEvent"],"InputEvent"]}]}]}}},{"EDValue":{"edValueName":{"Ident":"toUIEvent"},"edValueType":{"annotation":[{"start":[17,14],"name":".spago/web-uievents/v2.0.0/src/Web/UIEvent/InputEvent.purs","end":[17,35]},[]],"tag":"TypeApp","contents":[{"annotation":[{"start":[17,14],"name":".spago/web-uievents/v2.0.0/src/Web/UIEvent/InputEvent.purs","end":[17,35]},[]],"tag":"TypeApp","contents":[{"annotation":[{"start":[17,25],"name":".spago/web-uievents/v2.0.0/src/Web/UIEvent/InputEvent.purs","end":[17,27]},[]],"tag":"TypeConstructor","contents":[["Prim"],"Function"]},{"annotation":[{"start":[17,14],"name":".spago/web-uievents/v2.0.0/src/Web/UIEvent/InputEvent.purs","end":[17,24]},[]],"tag":"TypeConstructor","contents":[["Web","UIEvent","InputEvent"],"InputEvent"]}]},{"annotation":[{"start":[17,28],"name":".spago/web-uievents/v2.0.0/src/Web/UIEvent/InputEvent.purs","end":[17,35]},[]],"tag":"TypeConstructor","contents":[["Web","UIEvent","UIEvent"],"UIEvent"]}]}}},{"EDValue":{"edValueName":{"Ident":"toEvent"},"edValueType":{"annotation":[{"start":[20,12],"name":".spago/web-uievents/v2.0.0/src/Web/UIEvent/InputEvent.purs","end":[20,31]},[]],"tag":"TypeApp","contents":[{"annotation":[{"start":[20,12],"name":".spago/web-uievents/v2.0.0/src/Web/UIEvent/InputEvent.purs","end":[20,31]},[]],"tag":"TypeApp","contents":[{"annotation":[{"start":[20,23],"name":".spago/web-uievents/v2.0.0/src/Web/UIEvent/InputEvent.purs","end":[20,25]},[]],"tag":"TypeConstructor","contents":[["Prim"],"Function"]},{"annotation":[{"start":[20,12],"name":".spago/web-uievents/v2.0.0/src/Web/UIEvent/InputEvent.purs","end":[20,22]},[]],"tag":"TypeConstructor","contents":[["Web","UIEvent","InputEvent"],"InputEvent"]}]},{"annotation":[{"start":[20,26],"name":".spago/web-uievents/v2.0.0/src/Web/UIEvent/InputEvent.purs","end":[20,31]},[]],"tag":"TypeConstructor","contents":[["Web","Event","Internal","Types"],"Event"]}]}}},{"EDValue":{"edValueName":{"Ident":"data_"},"edValueType":{"annotation":[{"start":[23,25],"name":".spago/web-uievents/v2.0.0/src/Web/UIEvent/InputEvent.purs","end":[23,45]},[]],"tag":"TypeApp","contents":[{"annotation":[{"start":[23,25],"name":".spago/web-uievents/v2.0.0/src/Web/UIEvent/InputEvent.purs","end":[23,45]},[]],"tag":"TypeApp","contents":[{"annotation":[{"start":[23,36],"name":".spago/web-uievents/v2.0.0/src/Web/UIEvent/InputEvent.purs","end":[23,38]},[]],"tag":"TypeConstructor","contents":[["Prim"],"Function"]},{"annotation":[{"start":[23,25],"name":".spago/web-uievents/v2.0.0/src/Web/UIEvent/InputEvent.purs","end":[23,35]},[]],"tag":"TypeConstructor","contents":[["Web","UIEvent","InputEvent"],"InputEvent"]}]},{"annotation":[{"start":[23,39],"name":".spago/web-uievents/v2.0.0/src/Web/UIEvent/InputEvent.purs","end":[23,45]},[]],"tag":"TypeConstructor","contents":[["Prim"],"String"]}]}}},{"EDValue":{"edValueName":{"Ident":"isComposing"},"edValueType":{"annotation":[{"start":[25,31],"name":".spago/web-uievents/v2.0.0/src/Web/UIEvent/InputEvent.purs","end":[25,52]},[]],"tag":"TypeApp","contents":[{"annotation":[{"start":[25,31],"name":".spago/web-uievents/v2.0.0/src/Web/UIEvent/InputEvent.purs","end":[25,52]},[]],"tag":"TypeApp","contents":[{"annotation":[{"start":[25,42],"name":".spago/web-uievents/v2.0.0/src/Web/UIEvent/InputEvent.purs","end":[25,44]},[]],"tag":"TypeConstructor","contents":[["Prim"],"Function"]},{"annotation":[{"start":[25,31],"name":".spago/web-uievents/v2.0.0/src/Web/UIEvent/InputEvent.purs","end":[25,41]},[]],"tag":"TypeConstructor","contents":[["Web","UIEvent","InputEvent"],"InputEvent"]}]},{"annotation":[{"start":[25,45],"name":".spago/web-uievents/v2.0.0/src/Web/UIEvent/InputEvent.purs","end":[25,52]},[]],"tag":"TypeConstructor","contents":[["Prim"],"Boolean"]}]}}}],"efSourceSpan":{"start":[1,1],"name":".spago/web-uievents/v2.0.0/src/Web/UIEvent/InputEvent.purs","end":[25,52]}}